verification/alu testbench/defs.v
//-----------------------------------------------------------------
//
//            Diseño de Circuitos Integrados Digitales
//                   Trabajo Practico Final
//
//            Autor: Juan Pablo Tettamanti
//            Email: jptettamanti@gmail.com
//
//-----------------------------------------------------------------


//-----------------------------------------------------------------
// MCU Configuration
//-----------------------------------------------------------------
`define INST_WIDTH                              8
`define INST_DEPTH                              8
`define APSR_WIDTH                              3
`define ALUOP_WIDTH                             4

//-----------------------------------------------------------------
// PSR Fields
//-----------------------------------------------------------------
`define APSR_MIN                                2'd0
`define ZERO                                    2'd0
`define CARRY                                   2'd1
`define NEG                                     2'd2
`define APSR_MAX                                2'd2

//-----------------------------------------------------------------
// ALU Operations
//-----------------------------------------------------------------
`define ALU_ADD                                 4'b0000
`define ALU_SUB                                 4'b0001
`define ALU_ADDC                                4'b0010
`define ALU_SUBC                                4'b0011
`define ALU_NAND                                4'b0100
`define ALU_NOR                                 4'b0101
`define ALU_XOR                                 4'b0110
`define ALU_XNOR                                4'b0111
`define ALU_NOP                                 4'b1111

//-----------------------------------------------------------------
// Load/Store Instructions
//-----------------------------------------------------------------
`define MCU_LOAD                                8'b00000000
`define MCU_LOADI                               8'b00000001
`define MCU_STORE                               8'b00000010
`define MCU_STOREI                              8'b00000011

//-----------------------------------------------------------------
// Arithmetic Instructions
//-----------------------------------------------------------------
`define MCU_ADD                                 8'b01000000
`define MCU_SUB                                 8'b01000001
`define MCU_ADDC                                8'b01000010
`define MCU_SUBC                                8'b01000011
`define MCU_ADDI                                8'b01000100
`define MCU_SUBI                                8'b01000101
`define MCU_ADDCI                               8'b01000110
`define MCU_SUBCI                               8'b01000111

`define MCU_NAND                                8'b10000000
`define MCU_NOR                                 8'b10000001
`define MCU_XOR                                 8'b10000010
`define MCU_XNOR                                8'b10000011
`define MCU_NANDI                               8'b10000100
`define MCU_NORI                                8'b10000101
`define MCU_XORI                                8'b10000110
`define MCU_XNORI                               8'b10000111

//-----------------------------------------------------------------
// Jump Instructions
//-----------------------------------------------------------------
`define MCU_JUMP                                8'b11000000
`define MCU_JZ                                  8'b11000001
`define MCU_JC                                  8'b11000010
`define MCU_JN                                  8'b11000011

rtl/tests/pc_tb.v
//-----------------------------------------------------------------
//
//            Diseño de Circuitos Integrados Digitales
//                   Trabajo Practico Final
//
//            Autor: Juan Pablo Tettamanti
//            Email: jptettamanti@gmail.com
//
//-----------------------------------------------------------------


//-----------------------------------------------------------------
// Includes
//-----------------------------------------------------------------
`include "defs.v"

//-----------------------------------------------------------------
// Module - MCU Testbench
//-----------------------------------------------------------------
module tb_mcu ();

//-----------------------------------------------------------------
// Registers / Wires
//-----------------------------------------------------------------

reg                      tb_rst     ;      /* Reset signal */
reg                      tb_clk     ;      /* Clock signal */
reg                      tb_count   ;      /* Count signal */
reg                      tb_load    ;      /* New address load signal */
reg  [(`INST_DEPTH-1):0] tb_addr_in ;      /* New program address - after jump */
wire [(`INST_DEPTH-1):0] tb_addr_out;      /* Current program address */


//-----------------------------------------------------------------
// Instantiation
//-----------------------------------------------------------------

// Program Counter
pc
(
   .rst(tb_rst)          ,                 /* Reset signal */
   .clk(tb_clk)          ,                 /* Clock signal */
   .count(tb_count)      ,                 /* Count signal */
   .load(tb_load)        ,                 /* New address load signal */
   .addr_in(tb_addr_in)  ,                 /* New program address - after jump */
   .addr_out(tb_addr_out)                  /* Current program address */
);


//-----------------------------------------------------------------
// Initialize tasks
//-----------------------------------------------------------------
initial begin
   // Definir la base de datos VCD
   $dumpfile ("fsm.vcd");
   $dumpvars;
      
   // Definir la base de datos de Synopsys
//    $vcdplusfile("fsm.vpd");
//    $vcdpluson();
end

// Valores iniciales de las señales
initial begin
   tb_rst = 1'b1;
   tb_clk = 1'b0;
   tb_count = 1'b0;
   tb_load = 1'b0;
   tb_addr_in  = {`INST_DEPTH{1'b0}};
end



//-----------------------------------------------------------------
// Periodic tasks
//-----------------------------------------------------------------

// Generación de la señal de clock
always begin
   #5  tb_clk =  ~ tb_clk;
end

always
begin
   $display("Comienzo del testbench.");
   //$monitor("Clk: %b, Entrada: %b ; Salida: %b", tb_clk, tb_data_in, w_tick);

   @(negedge tb_clk)
   tb_rst = 1'b0;

   @(negedge tb_clk)
   @(negedge tb_clk)
   tb_count = 1'b1;
   
   @(negedge tb_clk)
   @(negedge tb_clk)
   @(negedge tb_clk)
   @(negedge tb_clk)
   @(negedge tb_clk)
   tb_addr_in  = (2**`INST_DEPTH)/4-1;
   tb_load     = 1'b1;

   @(negedge tb_clk)
   @(negedge tb_clk)
   tb_load = 1'b0;

   @(negedge tb_clk)
   @(negedge tb_clk)
   tb_count = 1'b0;

   @(negedge tb_clk)
   @(negedge tb_clk)
   $finish;
end
   
endmodule

verification/pc testbench/fsm.vcd
$date
	Sat Oct 19 18:28:37 2013
$end

$version
	Synopsys VCS version H-2013.06
$end

$timescale
	1s
$end

$comment Csum: 1 2230016e236d8fcc $end


$scope module tb_mcu $end
$var reg 1 ! tb_rst $end
$var reg 1 " tb_clk $end
$var reg 1 # tb_count $end
$var reg 1 $ tb_load $end
$var reg 8 % tb_addr_in [7:0] $end
$var wire 1 & tb_addr_out [7] $end
$var wire 1 ' tb_addr_out [6] $end
$var wire 1 ( tb_addr_out [5] $end
$var wire 1 ) tb_addr_out [4] $end
$var wire 1 * tb_addr_out [3] $end
$var wire 1 + tb_addr_out [2] $end
$var wire 1 , tb_addr_out [1] $end
$var wire 1 - tb_addr_out [0] $end

$scope module pc $end
$var wire 1 ! rst $end
$var wire 1 " clk $end
$var wire 1 # count $end
$var wire 1 $ load $end
$var wire 8 % addr_in [7:0] $end
$var reg 8 . addr_out [7:0] $end
$upscope $end

$upscope $end

$enddefinitions $end

#0
$dumpvars
0-
0,
0+
0*
0)
0(
0'
0&
0"
0#
0$
1!
b00000000 .
b00000000 %
$end
#5
1"
#10
0"
0!
#15
1"
#20
0"
#25
1"
#30
0"
1#
#35
1"
b00000001 .
1-
#40
0"
#45
1"
b00000010 .
1,
0-
#50
0"
#55
1"
b00000011 .
1-
#60
0"
#65
1"
b00000100 .
1+
0,
0-
#70
0"
#75
1"
b00000101 .
1-
#80
0"
b00111111 %
1$
#85
1"
b00111111 .
1(
1)
1*
1,
#90
0"
#95
1"
#100
0"
0$
#105
1"
b01000000 .
1'
0(
0)
0*
0+
0,
0-
#110
0"
#115
1"
b01000001 .
1-
#120
0"
0#
