verification/alu testbench/defs.v
//-----------------------------------------------------------------
//
//            Diseño de Circuitos Integrados Digitales
//                   Trabajo Practico Final
//
//            Autor: Juan Pablo Tettamanti
//            Email: jptettamanti@gmail.com
//
//-----------------------------------------------------------------


//-----------------------------------------------------------------
// MCU Configuration
//-----------------------------------------------------------------
`define INST_WIDTH                              8
`define INST_DEPTH                              8
`define APSR_WIDTH                              3
`define ALUOP_WIDTH                             4

//-----------------------------------------------------------------
// PSR Fields
//-----------------------------------------------------------------
`define APSR_MIN                                2'd0
`define ZERO                                    2'd0
`define CARRY                                   2'd1
`define NEG                                     2'd2
`define APSR_MAX                                2'd2

//-----------------------------------------------------------------
// ALU Operations
//-----------------------------------------------------------------
`define ALU_ADD                                 4'b0000
`define ALU_SUB                                 4'b0001
`define ALU_ADDC                                4'b0010
`define ALU_SUBC                                4'b0011
`define ALU_NAND                                4'b0100
`define ALU_NOR                                 4'b0101
`define ALU_XOR                                 4'b0110
`define ALU_XNOR                                4'b0111
`define ALU_NOP                                 4'b1111

//-----------------------------------------------------------------
// Load/Store Instructions
//-----------------------------------------------------------------
`define MCU_LOAD                                8'b00000000
`define MCU_LOADI                               8'b00000001
`define MCU_STORE                               8'b00000010
`define MCU_STOREI                              8'b00000011

//-----------------------------------------------------------------
// Arithmetic Instructions
//-----------------------------------------------------------------
`define MCU_ADD                                 8'b01000000
`define MCU_SUB                                 8'b01000001
`define MCU_ADDC                                8'b01000010
`define MCU_SUBC                                8'b01000011
`define MCU_ADDI                                8'b01000100
`define MCU_SUBI                                8'b01000101
`define MCU_ADDCI                               8'b01000110
`define MCU_SUBCI                               8'b01000111

`define MCU_NAND                                8'b10000000
`define MCU_NOR                                 8'b10000001
`define MCU_XOR                                 8'b10000010
`define MCU_XNOR                                8'b10000011
`define MCU_NANDI                               8'b10000100
`define MCU_NORI                                8'b10000101
`define MCU_XORI                                8'b10000110
`define MCU_XNORI                               8'b10000111

//-----------------------------------------------------------------
// Jump Instructions
//-----------------------------------------------------------------
`define MCU_JUMP                                8'b11000000
`define MCU_JZ                                  8'b11000001
`define MCU_JC                                  8'b11000010
`define MCU_JN                                  8'b11000011

verification/alu testbench/alu_tb.v
//-----------------------------------------------------------------
//
//            Diseño de Circuitos Integrados Digitales
//                   Trabajo Practico Final
//
//            Autor: Juan Pablo Tettamanti
//            Email: jptettamanti@gmail.com
//
//-----------------------------------------------------------------


//-----------------------------------------------------------------
// Includes
//-----------------------------------------------------------------
`include "defs.v"

//-----------------------------------------------------------------
// Module - MCU Testbench
//-----------------------------------------------------------------
module tb_alu ();

//-----------------------------------------------------------------
// Registers / Wires
//-----------------------------------------------------------------

reg  [`ALUOP_WIDTH-1:0]  tb_operation;         /* ALU operation */

reg  [`DATA_WIDTH-1:0]   tb_a_i      ;         /* First operand */
reg  [`DATA_WIDTH-1:0]   tb_b_i      ;         /* Second operand */
reg                      tb_psr      ;         /* Program Status Register */

wire [`DATA_WIDTH-1:0]   tb_result   ;         /* Result */
wire [`APSR_WIDTH-1:0]   tb_apsr     ;         /* Arithmetic PSR */


//-----------------------------------------------------------------
// Instantiation
//-----------------------------------------------------------------

alu
(
   .operation(tb_operation),         /* ALU operation */

   .a_i(tb_a_i)            ,         /* First operand */
   .b_i(tb_b_i)            ,         /* Second operand */
   .psr(tb_psr)            ,         /* Program Status Register */

   .result(tb_result)      ,         /* Result */
   .apsr(tb_apsr)                    /* Arithmetic PSR */
);


//-----------------------------------------------------------------
// Initialize tasks
//-----------------------------------------------------------------
initial begin
   // Definir la base de datos VCD
   $dumpfile ("fsm.vcd");
   $dumpvars;
      
   // Definir la base de datos de Synopsys
//    $vcdplusfile("fsm.vpd");
//    $vcdpluson();
end

// Valores iniciales de las señales
initial begin
   tb_a_i = {`DATA_WIDTH{1'b0}};
   tb_b_i = {`DATA_WIDTH{1'b0}};
   tb_psr = {`PSR_WIDTH{1'b0}};
   tb_operation = `ALU_NOP;
end



//-----------------------------------------------------------------
// Periodic tasks
//-----------------------------------------------------------------

always
begin
   $display("Comienzo del testbench.");
   //$monitor("Clk: %b, Entrada: %b ; Salida: %b", tb_clk, tb_data_in, w_tick);

   #10;
   tb_a_i = 8'hAE;
   tb_b_i = 8'hAE;
   tb_psr[`APSR_CARRY] = 1'b0;

   #10;
   tb_operation = `ALU_NOP;

   #10;
   tb_operation = `ALU_ADD;

   #10;
   tb_operation = `ALU_SUB;

   #10;
   tb_operation = `ALU_ADDC;

   #10;
   tb_operation = `ALU_SUBC;


   #10;
   tb_a_i = 8'hAA;
   tb_b_i = 8'hAA;
   tb_psr[`APSR_CARRY] = 1'b1;

   #10;
   tb_operation = `ALU_NOP;

   #10;
   tb_operation = `ALU_ADD;

   #10;
   tb_operation = `ALU_SUB;

   #10;
   tb_operation = `ALU_ADDC;

   #10;
   tb_operation = `ALU_SUBC;


   #10;
   tb_a_i = 8'hFF;
   tb_b_i = 8'h01;
   tb_psr[`APSR_CARRY] = 1'b0;

   #10;
   tb_operation = `ALU_NOP;

   #10;
   tb_operation = `ALU_ADD;

   #10;
   tb_operation = `ALU_SUB;

   #10;
   tb_operation = `ALU_ADDC;

   #10;
   tb_operation = `ALU_SUBC;


   #10;
   tb_a_i = 8'hFF;
   tb_b_i = 8'hFF;

   #10;
   tb_operation = `ALU_NAND;

   #10;
   tb_operation = `ALU_NOR;

   #10;
   tb_operation = `ALU_XOR;

   #10;
   tb_operation = `ALU_XNOR;


   #10;
   tb_a_i = 8'hFF;
   tb_b_i = 8'h00;

   #10;
   tb_operation = `ALU_NAND;

   #10;
   tb_operation = `ALU_NOR;

   #10;
   tb_operation = `ALU_XOR;

   #10;
   tb_operation = `ALU_XNOR;


   #10;
   tb_a_i = 8'hAA;
   tb_b_i = 8'hAA;

   #10;
   tb_operation = `ALU_XOR;

   #10;
   tb_operation = `ALU_XNOR;


   #10;
   tb_a_i = 8'hA7;
   tb_b_i = 8'h7A;

   #10;
   tb_operation = `ALU_XOR;

   #10;
   tb_operation = `ALU_XNOR;

   #10;
   #10;

   $finish;
end
   
endmodule

verification/alu testbench/fsm.vcd
$date
	Sun Oct 20 17:38:57 2013
$end

$version
	Synopsys VCS version H-2013.06
$end

$timescale
	1s
$end

$comment Csum: 1 4ffd0d49924ac665 $end


$scope module tb_alu $end
$var reg 4 ! tb_operation [3:0] $end
$var reg 8 " tb_a_i [7:0] $end
$var reg 8 # tb_b_i [7:0] $end
$var reg 1 $ tb_psr $end
$var wire 1 % tb_result [7] $end
$var wire 1 & tb_result [6] $end
$var wire 1 ' tb_result [5] $end
$var wire 1 ( tb_result [4] $end
$var wire 1 ) tb_result [3] $end
$var wire 1 * tb_result [2] $end
$var wire 1 + tb_result [1] $end
$var wire 1 , tb_result [0] $end
$var wire 1 - tb_apsr [2] $end
$var wire 1 . tb_apsr [1] $end
$var wire 1 / tb_apsr [0] $end

$scope module alu $end
$var wire 4 ! operation [3:0] $end
$var wire 8 " a_i [7:0] $end
$var wire 8 # b_i [7:0] $end
$var wire 1 $ psr $end
$var reg 8 0 result [7:0] $end
$var reg 1 1 apsr [2] $end
$var reg 1 2 apsr [1] $end
$var reg 1 3 apsr [0] $end
$upscope $end

$upscope $end

$enddefinitions $end

#0
$dumpvars
03
x2
x1
0/
x.
x-
0$
0,
0+
0*
0)
0(
0'
0&
0%
b00000000 0
b00000000 "
b00000000 #
b1111 !
$end
#10
b10101110 "
b10101110 #
b10101110 0
1%
1'
1)
1*
1+
#30
b0000 !
01
0-
b01011100 0
0%
1&
0'
1(
0+
12
1.
#40
b0001 !
02
0.
13
1/
b00000000 0
0&
0(
0)
0*
#50
b0010 !
x1
x-
x3
x/
bxxxxxxxx 0
x%
x&
x'
x(
x)
x*
x+
x,
x2
x.
#60
b0011 !
02
0.
#70
b10101010 "
b10101010 #
#80
b1111 !
03
0/
x2
x.
b10101010 0
1%
0&
1'
0(
1)
0*
1+
0,
#90
b0000 !
01
0-
b01010100 0
0%
1&
0'
1(
0)
1*
0+
12
1.
#100
b0001 !
02
0.
13
1/
b00000000 0
0&
0(
0*
#110
b0010 !
x1
x-
x3
x/
bxxxxxxxx 0
x%
x&
x'
x(
x)
x*
x+
x,
x2
x.
#120
b0011 !
02
0.
#130
b11111111 "
b00000001 #
#140
b1111 !
03
0/
x2
x.
b11111111 0
1%
1&
1'
1(
1)
1*
1+
1,
#150
b0000 !
01
0-
13
1/
b00000000 0
0%
0&
0'
0(
0)
0*
0+
0,
12
1.
#160
b0001 !
02
0.
11
1-
03
0/
b11111110 0
1%
1&
1'
1(
1)
1*
1+
#170
b0010 !
x1
x-
x3
x/
bxxxxxxxx 0
x%
x&
x'
x(
x)
x*
x+
x,
x2
x.
#180
b0011 !
02
0.
#190
b11111111 #
#200
b0100 !
01
0-
13
1/
b00000000 0
0%
0&
0'
0(
0)
0*
0+
0,
#210
b0101 !
#220
b0110 !
#230
b0111 !
11
1-
03
0/
b11111111 0
1%
1&
1'
1(
1)
1*
1+
1,
#240
b00000000 #
01
0-
13
1/
b00000000 0
0%
0&
0'
0(
0)
0*
0+
0,
#250
b0100 !
11
1-
03
0/
b11111111 0
1%
1&
1'
1(
1)
1*
1+
1,
#260
b0101 !
01
0-
13
1/
b00000000 0
0%
0&
0'
0(
0)
0*
0+
0,
#270
b0110 !
11
1-
03
0/
b11111111 0
1%
1&
1'
1(
1)
1*
1+
1,
#280
b0111 !
01
0-
13
1/
b00000000 0
0%
0&
0'
0(
0)
0*
0+
0,
#290
b10101010 "
b10101010 #
11
1-
03
0/
b11111111 0
1%
1&
1'
1(
1)
1*
1+
1,
#300
b0110 !
01
0-
13
1/
b00000000 0
0%
0&
0'
0(
0)
0*
0+
0,
#310
b0111 !
11
1-
03
0/
b11111111 0
1%
1&
1'
1(
1)
1*
1+
1,
#320
b10100111 "
b01111010 #
01
0-
b00100010 0
0%
0&
0(
0)
0*
0,
#330
b0110 !
11
1-
b11011101 0
1%
1&
0'
1(
1)
1*
0+
1,
#340
b0111 !
01
0-
b00100010 0
0%
0&
1'
0(
0)
0*
1+
0,
